lds_org.py
LDS_org-0.2.1.dist-info/DESCRIPTION.rst
LDS_org-0.2.1.dist-info/METADATA
LDS_org-0.2.1.dist-info/RECORD
LDS_org-0.2.1.dist-info/WHEEL
LDS_org-0.2.1.dist-info/metadata.json
LDS_org-0.2.1.dist-info/top_level.txt
