Metadata-Version: 2.0
Name: LDS-org
Version: 0.2.1
Summary: Access LDS.org json information
Home-page: https://www.github.com/jidn/lds-org/
Author: Clinton James
Author-email: clinton.james@anuit.com
License: MIT License
Download-URL: https://github.com/jidn/lds-org/tarball/0.2.1
Keywords: lds
Platform: UNKNOWN
Classifier: Development Status :: 3 - Alpha
Classifier: Intended Audience :: Developers
Classifier: License :: OSI Approved :: MIT License
Classifier: Environment :: Web Environment
Classifier: License :: OSI Approved :: Apache Software License
Classifier: Programming Language :: Python :: 2.7
Requires-Dist: requests
Requires-Dist: certifi
